kronos/__init__.py
kronos/kronos.py
kronos/utilities.py
kronos_daterange-0.0.13.dist-info/LICENSE.rst
kronos_daterange-0.0.13.dist-info/WHEEL
kronos_daterange-0.0.13.dist-info/METADATA
kronos_daterange-0.0.13.dist-info/RECORD
