Metadata-Version: 2.1
Name: kronos-daterange
Version: 0.0.13
Summary: Kronos makes date ranges easier.
Home-page: https://github.com/nat5142/kronos
Keywords: kronos,kronos-daterange,daterange
Author: Nick Tulli
Author-email: ntulli.dev@gmail.com
Requires-Python: >=3.7,<3.11
Classifier: Development Status :: 2 - Pre-Alpha
Classifier: Intended Audience :: Developers
Classifier: License :: OSI Approved :: BSD License
Classifier: Natural Language :: English
Classifier: Programming Language :: Python :: 3
Classifier: Programming Language :: Python :: 3.10
Classifier: Programming Language :: Python :: 3.7
Classifier: Programming Language :: Python :: 3.8
Classifier: Programming Language :: Python :: 3.9
Requires-Dist: python-dateutil (>=2.8.2,<3.0.0)
Requires-Dist: pytz (>=2022.1,<2023.0)
Project-URL: Bug Tracker, https://github.com/nat5142/kronos/issues
Project-URL: Documentation, https://nat5142-kronos.readthedocs.io/
Project-URL: Repository, https://github.com/nat5142/kronos
